robotcode/language_server/__init__.py
robotcode/language_server/__version__.py
robotcode/language_server/cli.py
robotcode/language_server/hooks.py
robotcode/language_server/py.typed
robotcode/language_server/common/__init__.py
robotcode/language_server/common/decorators.py
robotcode/language_server/common/protocol.py
robotcode/language_server/common/server.py
robotcode/language_server/common/parts/__init__.py
robotcode/language_server/common/parts/code_action.py
robotcode/language_server/common/parts/code_lens.py
robotcode/language_server/common/parts/commands.py
robotcode/language_server/common/parts/completion.py
robotcode/language_server/common/parts/declaration.py
robotcode/language_server/common/parts/definition.py
robotcode/language_server/common/parts/diagnostics.py
robotcode/language_server/common/parts/document_highlight.py
robotcode/language_server/common/parts/document_symbols.py
robotcode/language_server/common/parts/documents.py
robotcode/language_server/common/parts/folding_range.py
robotcode/language_server/common/parts/formatting.py
robotcode/language_server/common/parts/hover.py
robotcode/language_server/common/parts/implementation.py
robotcode/language_server/common/parts/inlay_hint.py
robotcode/language_server/common/parts/inline_value.py
robotcode/language_server/common/parts/linked_editing_ranges.py
robotcode/language_server/common/parts/protocol_part.py
robotcode/language_server/common/parts/references.py
robotcode/language_server/common/parts/rename.py
robotcode/language_server/common/parts/selection_range.py
robotcode/language_server/common/parts/semantic_tokens.py
robotcode/language_server/common/parts/signature_help.py
robotcode/language_server/common/parts/window.py
robotcode/language_server/common/parts/workspace.py
robotcode/language_server/common/parts/workspace_symbols.py
robotcode/language_server/robotframework/__init__.py
robotcode/language_server/robotframework/configuration.py
robotcode/language_server/robotframework/protocol.py
robotcode_language_server-2.0.1.dist-info/METADATA
robotcode_language_server-2.0.1.dist-info/WHEEL
robotcode_language_server-2.0.1.dist-info/entry_points.txt
robotcode_language_server-2.0.1.dist-info/RECORD
